{
  "case_id": "HCBM020020461982_1_2007-03-16",
  "court": "Madras High Court",
  "date": null,
  "judges": [],
  "petitioners": [],
  "respondents": [],
  "acts_referred": [],
  "judgment_text": "IN THE HIGH COURT OF JUDICATURE AT BOMBAY\n IN THE HIGH COURT OF JUDICATURE AT BOMBAY\n IN THE HIGH COURT OF JUDICATURE AT BOMBAY\n ORDINARY ORIGINAL CIVIL JURISDICTION \n ORDINARY ORIGINAL CIVIL JURISDICTION \n ORDINARY ORIGINAL CIVIL JURISDICTION \n SUIT NO.1897 OF 1982.\n SUIT NO.1897 OF 1982.\n SUIT NO.1897 OF 1982.\n\n M/s. S. Raj & Co,. ..Plaintiff\n versus\n Pushpa K. Wadhwa & Ors. ..Defendants\n Mr.Amish M. Shroff i/b. Humranwala & Co. for the\n Plaintiff\n Mr.N.N.Vaishnawa for the defendant\n Coram : S.R.Sathe, J.\n Coram : S.R.Sathe, J.\n Coram : S.R.Sathe, J.\n Dated : 16th March, 2007\n Dated : 16th March, 2007\n Dated : 16th March, 2007\n P.C.\n 1. Today the plaintiffs have tendered the\n compliation of documents. The learned advocate for\n the plaintiff undertakes to give the copy of the\n compilation of documents within one week to the\n defendants. Hence S.O. to 23.3.2007\n (S.R.Sathe, J.)\n (S.R.Sathe, J.)\n (S.R.Sathe, J.)\n\n pps."
}